setup.py
sivchain/__init__.py
sivchain.egg-info/PKG-INFO
sivchain.egg-info/SOURCES.txt
sivchain.egg-info/dependency_links.txt
sivchain.egg-info/not-zip-safe
sivchain.egg-info/top_level.txt