Metadata-Version: 1.1
Name: sivchain
Version: 0.0.0
Summary: AES-SIV and CHAIN symmetric encryption
Home-page: https://github.com/zcred/sivchain/tree/master/python/
Author: Tony Arcieri
Author-email: bascule@gmail.com
License: MIT license
Keywords: cryptography,encryption,security,streaming
Platform: UNKNOWN
Classifier: Development Status :: 2 - Pre-Alpha
Classifier: Intended Audience :: Developers
Classifier: License :: OSI Approved :: MIT License
Classifier: Natural Language :: English
